{
  "total_chars": 1855,
  "avg_sentence_len": 22.4,
  "sentence_len_std": 14.6,
  "avg_paragraph_len": 26,
  "paragraph_len_range": {
    "min": 6,
    "max": 70
  },
  "vocabulary_diversity": 0.33,
  "top_patterns": [
    "原溯(10次)",
    "蒲雨(8次)",
    "陆蓁(4次)",
    "“那(3次)"
  ],
  "rhetorical_features": [
    "短句节奏(4处)"
  ],
  "simile_count": 2,
  "ai_marker_count": 0,
  "direct_emotion_count": 1,
  "ellipsis_count": 4,
  "has_said_tag": true,
  "has_emotion_words": true,
  "end_punctuations": {
    "句号": 36,
    "问号": 0,
    "叹号": 0,
    "引号": 0
  },
  "chapter": 40,
  "file": "第40章.txt"
}