{
  "total_chars": 1851,
  "avg_sentence_len": 23.2,
  "sentence_len_std": 16.5,
  "avg_paragraph_len": 39,
  "paragraph_len_range": {
    "min": 6,
    "max": 112
  },
  "vocabulary_diversity": 0.275,
  "top_patterns": [
    "李命(12次)",
    "谭青(6次)"
  ],
  "rhetorical_features": [
    "短句节奏(9处)"
  ],
  "simile_count": 2,
  "ai_marker_count": 1,
  "direct_emotion_count": 0,
  "ellipsis_count": 7,
  "has_said_tag": true,
  "has_emotion_words": true,
  "end_punctuations": {
    "句号": 19,
    "问号": 2,
    "叹号": 15,
    "引号": 0
  },
  "chapter": 74,
  "file": "第74章.txt"
}