{
  "total_chars": 2426,
  "avg_sentence_len": 35.6,
  "sentence_len_std": 22.6,
  "avg_paragraph_len": 40,
  "paragraph_len_range": {
    "min": 6,
    "max": 112
  },
  "vocabulary_diversity": 0.241,
  "top_patterns": [
    "王馨(8次)",
    "谭青(5次)",
    "可是(4次)"
  ],
  "rhetorical_features": [],
  "simile_count": 2,
  "ai_marker_count": 1,
  "direct_emotion_count": 1,
  "ellipsis_count": 49,
  "has_said_tag": false,
  "has_emotion_words": true,
  "end_punctuations": {
    "句号": 12,
    "问号": 1,
    "叹号": 12,
    "引号": 0
  },
  "chapter": 171,
  "file": "第171章.txt"
}